lambdata_henry/__init__.py
lambdata_henry/henry1.py
lambdata_henry-0.0.3.dist-info/LICENSE
lambdata_henry-0.0.3.dist-info/METADATA
lambdata_henry-0.0.3.dist-info/WHEEL
lambdata_henry-0.0.3.dist-info/top_level.txt
lambdata_henry-0.0.3.dist-info/RECORD
