Metadata-Version: 2.1
Name: lambdata-henry
Version: 0.0.3
Summary: date_extract, state-abbreviation
Home-page: https://github.com/henryspg/lambdata
Author: Henry Gultom
Author-email: henryspg@gmail.com
License: UNKNOWN
Platform: UNKNOWN
Classifier: Programming Language :: Python :: 3
Classifier: License :: OSI Approved :: MIT License
Classifier: Operating System :: OS Independent
Requires-Python: >=3.6
Requires-Dist: numpy
Requires-Dist: pandas
